{
  "version": "7",
  "dialect": "postgresql",
  "entries": [
    {
      "idx": 0,
      "version": "7",
      "when": 1725693392986,
      "tag": "0000_sleepy_mantis",
      "breakpoints": true
    },
    {
      "idx": 1,
      "version": "7",
      "when": 1725694279627,
      "tag": "0001_awesome_screwball",
      "breakpoints": true
    },
    {
      "idx": 2,
      "version": "7",
      "when": 1725696825500,
      "tag": "0002_strong_dagger",
      "breakpoints": true
    },
    {
      "idx": 3,
      "version": "7",
      "when": 1725701641898,
      "tag": "0003_amused_maginty",
      "breakpoints": true
    },
    {
      "idx": 4,
      "version": "7",
      "when": 1725703152938,
      "tag": "0004_short_baron_strucker",
      "breakpoints": true
    },
    {
      "idx": 5,
      "version": "7",
      "when": 1725716896317,
      "tag": "0005_rich_valkyrie",
      "breakpoints": true
    },
    {
      "idx": 6,
      "version": "7",
      "when": 1725729918570,
      "tag": "0006_previous_kat_farrell",
      "breakpoints": true
    },
    {
      "idx": 7,
      "version": "7",
      "when": 1725732238943,
      "tag": "0007_lean_gwen_stacy",
      "breakpoints": true
    },
    {
      "idx": 8,
      "version": "7",
      "when": 1725734365805,
      "tag": "0008_opposite_paibok",
      "breakpoints": true
    },
    {
      "idx": 9,
      "version": "7",
      "when": 1725735307685,
      "tag": "0009_dear_starjammers",
      "breakpoints": true
    },
    {
      "idx": 10,
      "version": "7",
      "when": 1725748942885,
      "tag": "0010_lean_rockslide",
      "breakpoints": true
    },
    {
      "idx": 11,
      "version": "7",
      "when": 1725749674605,
      "tag": "0011_short_king_cobra",
      "breakpoints": true
    },
    {
      "idx": 12,
      "version": "7",
      "when": 1725749692714,
      "tag": "0012_faulty_firedrake",
      "breakpoints": true
    }
  ]
}